compose_paas/__init__.py
compose_paas/config.py
compose_paas/main.py
compose_paas/platform/__init__.py
compose_paas/platform/marathon.py
compose_paas/platform/singularity.py
compose_paas-1.0.3.dist-info/METADATA
compose_paas-1.0.3.dist-info/RECORD
compose_paas-1.0.3.dist-info/WHEEL
compose_paas-1.0.3.dist-info/entry_points.txt
compose_paas-1.0.3.dist-info/top_level.txt
