Metadata-Version: 2.1
Name: compose-paas
Version: 1.0.3
Summary: Deploy to multiple container platforms/PAAS using docker-compose files
Home-page: https://github.com/bidhan-a/compose-paas
Author: Bidhan Adhikary
Author-email: bidhan619@gmail.com
License: BSD license
Keywords: compose-paas
Platform: UNKNOWN
Classifier: Development Status :: 2 - Pre-Alpha
Classifier: Intended Audience :: Developers
Classifier: License :: OSI Approved :: BSD License
Classifier: Natural Language :: English
Classifier: Programming Language :: Python :: 2
Classifier: Programming Language :: Python :: 2.7
Classifier: Programming Language :: Python :: 3
Classifier: Programming Language :: Python :: 3.4
Classifier: Programming Language :: Python :: 3.5
Classifier: Programming Language :: Python :: 3.6
Requires-Dist: PyYAML
Requires-Dist: requests
Requires-Dist: six
